social_auth_storage_sqlalchemy-1.1.0.dist-info/DESCRIPTION.rst
social_auth_storage_sqlalchemy-1.1.0.dist-info/METADATA
social_auth_storage_sqlalchemy-1.1.0.dist-info/RECORD
social_auth_storage_sqlalchemy-1.1.0.dist-info/WHEEL
social_auth_storage_sqlalchemy-1.1.0.dist-info/metadata.json
social_auth_storage_sqlalchemy-1.1.0.dist-info/top_level.txt
social_sqlalchemy/__init__.py
social_sqlalchemy/storage.py
